grid_table_py/__init__.py
grid_table_py/grid_table_py.py
grid_table_py/support/__init__.py
grid_table_py/support/markdown_table_builder.py
grid_table_py/support/table_ingest.py
grid_table_py-0.1.1.dist-info/entry_points.txt
grid_table_py-0.1.1.dist-info/LICENSE
grid_table_py-0.1.1.dist-info/WHEEL
grid_table_py-0.1.1.dist-info/METADATA
grid_table_py-0.1.1.dist-info/RECORD
