Metadata-Version: 2.1
Name: grid-table-py
Version: 0.1.1
Summary: 
License: MIT
Author: FSharp4
Author-email: 33583307+FSharp4@users.noreply.github.com
Requires-Python: >=3.11,<3.12
Classifier: License :: OSI Approved :: MIT License
Classifier: Programming Language :: Python :: 3
Classifier: Programming Language :: Python :: 3.11
Requires-Dist: pandas (>=1.5.1,<2.0.0)
Requires-Dist: tabulate (>=0.9.0,<0.10.0)
